SSp_Detector/__init__.py
SSp_Detector/__version__.py
SSp_Detector/ssp_detector.py
SSp_Detector-2024.12.13.dist-info/LICENSE
SSp_Detector-2024.12.13.dist-info/METADATA
SSp_Detector-2024.12.13.dist-info/WHEEL
SSp_Detector-2024.12.13.dist-info/top_level.txt
SSp_Detector-2024.12.13.dist-info/RECORD
