Metadata-Version: 2.1
Name: SSp_Detector
Version: 2024.12.13
Summary: Sleep spindles detector
Home-page: https://github.com/sjg2203/SSp_Detector
Author: Simon J. Guillot
Author-email: simon.guillot@inserm.fr
License: Apache 2.0 license
Classifier: Development Status :: 5 - Production/Stable
Classifier: Intended Audience :: Science/Research
Classifier: License :: OSI Approved :: Apache Software License
Classifier: Operating System :: Unix
Classifier: Operating System :: MacOS
Classifier: Operating System :: Microsoft :: Windows
Classifier: Programming Language :: Python :: 3 :: Only
Classifier: Programming Language :: Python :: 3
Classifier: Programming Language :: Python :: 3.10
Classifier: Programming Language :: Python :: 3.11
Classifier: Programming Language :: Python :: 3.12
License-File: LICENSE
Requires-Dist: mne>=1.5.1
Requires-Dist: outdated
Requires-Dist: numpy>=1.24.3
Requires-Dist: pandas>=2.0.0
Requires-Dist: scipy>=1.11
